idling_at_home/__init__.py
idling_at_home/idle.py
idling_at_home/main.py
idling_at_home-2021.1.dist-info/COPYING
idling_at_home-2021.1.dist-info/METADATA
idling_at_home-2021.1.dist-info/WHEEL
idling_at_home-2021.1.dist-info/entry_points.txt
idling_at_home-2021.1.dist-info/top_level.txt
idling_at_home-2021.1.dist-info/RECORD
