Metadata-Version: 2.1
Name: idling-at-home
Version: 2021.1
Summary: Start Folding@Home when your computer is idle.
Home-page: https://github.com/NFJones/idling-at-home
Author: Neil F Jones
License: UNKNOWN
Keywords: folding home folding@home
Platform: UNKNOWN
Classifier: License :: OSI Approved :: MIT License
Classifier: Programming Language :: Python :: 3
Requires-Python: >=3.5, <4
Requires-Dist: psutil
Requires-Dist: PyFoldingAtHomeControl
